{"_type":"export","__export_format":4,"__export_date":"2020-04-11T23:31:35.442Z","__export_source":"insomnia.desktop.app:v7.1.1","resources":[{"_id":"req_21b76160a14d4ac88c12266635a0eaad","authentication":{},"body":{},"created":1586298090548,"description":"","headers":[],"isPrivate":false,"metaSortKey":-1586298090649,"method":"GET","modified":1586563278271,"name":"List","parameters":[],"parentId":"fld_54199f6ee127426b9f2d1faac517f0ba","settingDisableRenderRequestBody":false,"settingEncodeUrl":true,"settingFollowRedirects":"global","settingRebuildPath":true,"settingSendCookies":true,"settingStoreCookies":true,"url":" {{ base_url  }}/repositories","_type":"request"},{"_id":"fld_54199f6ee127426b9f2d1faac517f0ba","created":1586557892932,"description":"","environment":{},"environmentPropertyOrder":null,"metaSortKey":-1586557892932,"modified":1586557892932,"name":"Test NodeJs - 1","parentId":"wrk_172cce81d8014dfdb450157e79be9405","_type":"request_group"},{"_id":"wrk_172cce81d8014dfdb450157e79be9405","created":1586297842817,"description":"","modified":1586297842817,"name":"Insomnia","parentId":null,"_type":"workspace"},{"_id":"req_45185c5ef6914c84893b2337fbd45b1b","authentication":{},"body":{"mimeType":"application/json","text":"{\n\t\"title\": \"Desafio Node.js\",\n\t\"url\": \"http://github.com/teste-node-js\",\n\t\"techs\": [\"Node.js\", \"PHP\", \"Java\"],\n\t\"likes\": 0\t\n}"},"created":1586557908350,"description":"","headers":[{"id":"pair_61898ba0bce64391b55d559b5c082432","name":"Content-Type","value":"application/json"}],"isPrivate":false,"metaSortKey":-1586298090599,"method":"POST","modified":1586558094100,"name":"Create","parameters":[],"parentId":"fld_54199f6ee127426b9f2d1faac517f0ba","settingDisableRenderRequestBody":false,"settingEncodeUrl":true,"settingFollowRedirects":"global","settingRebuildPath":true,"settingSendCookies":true,"settingStoreCookies":true,"url":" {{ base_url  }}/repositories","_type":"request"},{"_id":"req_35a37e05c31b43ff945cb048c75dbad5","authentication":{},"body":{"mimeType":"application/json","text":"{\n\t\"title\": \"Desafio Node.js TESTE MESA\",\n\t\"url\": \"http://github.com/teste-node-js\",\n\t\"techs\": [\"Node.js\", \"PHP\", \"Java\"]\n}"},"created":1586298320041,"description":"","headers":[{"id":"pair_48d5016966a94b35a54caa907470f875","name":"Content-Type","value":"application/json"}],"isPrivate":false,"metaSortKey":-1586298090549,"method":"PUT","modified":1586563292069,"name":"Update","parameters":[],"parentId":"fld_54199f6ee127426b9f2d1faac517f0ba","settingDisableRenderRequestBody":false,"settingEncodeUrl":true,"settingFollowRedirects":"global","settingRebuildPath":true,"settingSendCookies":true,"settingStoreCookies":true,"url":" {{ base_url  }}/repositories/50c39e33-bbc2-422d-87cf-e2afe0bc7287","_type":"request"},{"_id":"req_8f19fff96a4d4f77a98265f997150b94","authentication":{},"body":{},"created":1586557926056,"description":"","headers":[],"isPrivate":false,"metaSortKey":-1586298090499,"method":"DELETE","modified":1586563326669,"name":"Delete","parameters":[],"parentId":"fld_54199f6ee127426b9f2d1faac517f0ba","settingDisableRenderRequestBody":false,"settingEncodeUrl":true,"settingFollowRedirects":"global","settingRebuildPath":true,"settingSendCookies":true,"settingStoreCookies":true,"url":" {{ base_url  }}/repositories/50c39e33-bbc2-422d-87cf-e2afe0bc7287","_type":"request"},{"_id":"req_3aae022d96744eee8b96db234c225c58","authentication":{},"body":{"mimeType":"application/json","text":""},"created":1586561240344,"description":"","headers":[{"id":"pair_61898ba0bce64391b55d559b5c082432","name":"Content-Type","value":"application/json"}],"isPrivate":false,"metaSortKey":-1586298090449,"method":"POST","modified":1586563711787,"name":"Increment Likes","parameters":[],"parentId":"fld_54199f6ee127426b9f2d1faac517f0ba","settingDisableRenderRequestBody":false,"settingEncodeUrl":true,"settingFollowRedirects":"global","settingRebuildPath":true,"settingSendCookies":true,"settingStoreCookies":true,"url":" {{ base_url  }}/repositories/d5b963a3-cbdf-43a9-882a-25ef0fa88a82/like","_type":"request"},{"_id":"env_8f255260a5f2bd7141cee020445b4c6585e13b5f","color":null,"created":1586297842868,"data":{},"dataPropertyOrder":null,"isPrivate":false,"metaSortKey":1586297842868,"modified":1586297842868,"name":"Base Environment","parentId":"wrk_172cce81d8014dfdb450157e79be9405","_type":"environment"},{"_id":"jar_8f255260a5f2bd7141cee020445b4c6585e13b5f","cookies":[],"created":1586297842870,"modified":1586297842870,"name":"Default Jar","parentId":"wrk_172cce81d8014dfdb450157e79be9405","_type":"cookie_jar"},{"_id":"env_d2a75421f9bb46f48cf307f935b8416a","color":"#7964ce","created":1586297927536,"data":{"base_url":"http://localhost:3333"},"dataPropertyOrder":{"&":["base_url"]},"isPrivate":false,"metaSortKey":1586297927536,"modified":1586297965635,"name":"dev","parentId":"env_8f255260a5f2bd7141cee020445b4c6585e13b5f","_type":"environment"},{"_id":"env_0a3e8de82d83458a9f61da493014c009","color":"#00830e","created":1586297973088,"data":{"base_url":"http://localhost:3333"},"dataPropertyOrder":{"&":["base_url"]},"isPrivate":false,"metaSortKey":1586297973088,"modified":1586297989847,"name":"production","parentId":"env_8f255260a5f2bd7141cee020445b4c6585e13b5f","_type":"environment"}]}